NetkillerDatabase/README.md
NetkillerDatabase/__init__.py
NetkillerDatabase/__main__.py
NetkillerDatabase/file.epub
NetkillerDatabase/index.html
NetkillerDatabase/css/__init__.py
NetkillerDatabase/css/annotations.css
NetkillerDatabase/css/main.css
NetkillerDatabase/css/normalize.css
NetkillerDatabase/css/popup.css
NetkillerDatabase/font/__init__.py
NetkillerDatabase/font/fontello.eot
NetkillerDatabase/font/fontello.svg
NetkillerDatabase/font/fontello.ttf
NetkillerDatabase/font/fontello.woff
NetkillerDatabase/img/__init__.py
NetkillerDatabase/img/annotator-glyph-sprite.png
NetkillerDatabase/img/annotator-icon-sprite.png
NetkillerDatabase/img/apple-touch-icon.png
NetkillerDatabase/img/cancelfullscreen.png
NetkillerDatabase/img/close.png
NetkillerDatabase/img/fullscreen.png
NetkillerDatabase/img/loader.gif
NetkillerDatabase/img/menu-icon.png
NetkillerDatabase/img/save.png
NetkillerDatabase/img/saved.png
NetkillerDatabase/img/settings-s.png
NetkillerDatabase/img/settings.png
NetkillerDatabase/img/star.png
NetkillerDatabase/js/__init__.py
NetkillerDatabase/js/epub.js
NetkillerDatabase/js/epub.min.js
NetkillerDatabase/js/epub.min.map
NetkillerDatabase/js/hooks.min.js
NetkillerDatabase/js/hooks.min.map
NetkillerDatabase/js/reader.js
NetkillerDatabase/js/reader.js.map
NetkillerDatabase/js/reader.min.js
NetkillerDatabase/js/reader.min.map
NetkillerDatabase/js/hooks/__init__.py
NetkillerDatabase/js/hooks/extensions/__init__.py
NetkillerDatabase/js/hooks/extensions/highlight.js
NetkillerDatabase/js/libs/__init__.py
NetkillerDatabase/js/libs/jquery.min.js
NetkillerDatabase/js/libs/localforage.min.js
NetkillerDatabase/js/libs/screenfull.js
NetkillerDatabase/js/libs/screenfull.min.js
NetkillerDatabase/js/libs/zip.min.js
NetkillerDatabase/js/plugins/__init__.py
NetkillerDatabase/js/plugins/hypothesis.js
NetkillerDatabase/js/plugins/search.js
netkiller_database-2024.3.5.0.dist-info/METADATA
netkiller_database-2024.3.5.0.dist-info/WHEEL
netkiller_database-2024.3.5.0.dist-info/entry_points.txt
netkiller_database-2024.3.5.0.dist-info/top_level.txt
netkiller_database-2024.3.5.0.dist-info/RECORD
